cohpy/__init__.py
cohpy/client.py
cohpy/constants.py
cohpy/endpoint.py
cohpy/exceptions.py
cohpy/leaderboards.py
cohpy/tests/__init__.py
cohpy/tests/test_all_leaderboards.py
cohpy/tests/test_personal_stat.py
cohpy/tests/test_player_match_history.py
cohpy/tests/test_specific_leaderboard.py
cohpy-1.1.4.dist-info/LICENSE
cohpy-1.1.4.dist-info/METADATA
cohpy-1.1.4.dist-info/WHEEL
cohpy-1.1.4.dist-info/RECORD
