Metadata-Version: 2.1
Name: cohpy
Version: 1.1.4
Summary: 
Author: Andres Garrido
Author-email: andreslp0001@gmail.com
Requires-Python: >=3.10,<4.0
Classifier: Programming Language :: Python :: 3
Classifier: Programming Language :: Python :: 3.10
Classifier: Programming Language :: Python :: 3.11
Requires-Dist: coverage (>=7.2.7,<8.0.0)
Requires-Dist: flake8 (>=6.1.0,<7.0.0)
Requires-Dist: flake8-import-order (>=0.18.2,<0.19.0)
Requires-Dist: requests (>=2.31.0,<3.0.0)
